{
  "config": {
    "configFile": "/Users/julianclarkson/Documents/flyingbluewhale/playwright.audit.config.ts",
    "rootDir": "/Users/julianclarkson/Documents/flyingbluewhale/e2e/audit",
    "forbidOnly": false,
    "fullyParallel": false,
    "globalSetup": null,
    "globalTeardown": null,
    "globalTimeout": 0,
    "grep": {},
    "grepInvert": null,
    "maxFailures": 0,
    "metadata": {
      "actualWorkers": 1
    },
    "preserveOutput": "always",
    "projects": [
      {
        "outputDir": "/Users/julianclarkson/Documents/flyingbluewhale/test-results",
        "repeatEach": 1,
        "retries": 0,
        "metadata": {
          "actualWorkers": 1
        },
        "id": "webkit",
        "name": "webkit",
        "testDir": "/Users/julianclarkson/Documents/flyingbluewhale/e2e/audit",
        "testIgnore": [],
        "testMatch": [
          "**/*.@(spec|test).?(c|m)[jt]s?(x)"
        ],
        "timeout": 60000
      }
    ],
    "quiet": false,
    "reporter": [
      [
        "list",
        null
      ],
      [
        "json",
        {
          "outputFile": "docs/audits/evidence/report.json"
        }
      ]
    ],
    "reportSlowTests": {
      "max": 5,
      "threshold": 300000
    },
    "shard": null,
    "tags": [],
    "updateSnapshots": "missing",
    "updateSourceMethod": "patch",
    "version": "1.59.1",
    "workers": 1,
    "webServer": {
      "command": "npm run dev",
      "url": "http://localhost:3000",
      "reuseExistingServer": true,
      "timeout": 90000
    }
  },
  "suites": [
    {
      "title": "themes-responsive.spec.ts",
      "file": "themes-responsive.spec.ts",
      "column": 0,
      "line": 0,
      "specs": [],
      "suites": [
        {
          "title": "matrix · marketing-customers",
          "file": "themes-responsive.spec.ts",
          "line": 129,
          "column": 8,
          "specs": [
            {
              "title": "bento · tablet (768px)",
              "ok": true,
              "tags": [],
              "tests": [
                {
                  "timeout": 60000,
                  "annotations": [],
                  "expectedStatus": "passed",
                  "projectId": "webkit",
                  "projectName": "webkit",
                  "results": [
                    {
                      "workerIndex": 0,
                      "parallelIndex": 0,
                      "status": "passed",
                      "duration": 677,
                      "errors": [],
                      "stdout": [],
                      "stderr": [],
                      "retry": 0,
                      "startTime": "2026-04-20T14:26:06.254Z",
                      "annotations": [],
                      "attachments": []
                    }
                  ],
                  "status": "expected"
                }
              ],
              "id": "1c89d04aa7940a54dcf2-35583fd1bef95bc818cf",
              "file": "themes-responsive.spec.ts",
              "line": 132,
              "column": 13
            }
          ]
        }
      ]
    }
  ],
  "errors": [],
  "stats": {
    "startTime": "2026-04-20T14:26:05.667Z",
    "duration": 1455.09,
    "expected": 1,
    "skipped": 0,
    "unexpected": 0,
    "flaky": 0
  }
}