{
  "console.projects.portfolio.title": "Portfolio-Status",
  "console.projects.portfolio.legend.onTrack": "Im Plan ${counts.green}",
  "console.projects.portfolio.legend.watch": "Beobachtung ${counts.amber}",
  "console.projects.portfolio.legend.atRisk": "Gefährdet ${counts.red}",
  "console.projects.portfolio.schedule.noEnd": "kein Ende",
  "console.projects.portfolio.schedule.daysOver": "${-days}T überfällig",
  "console.projects.portfolio.schedule.endsToday": "endet heute",
  "console.projects.portfolio.schedule.daysLeft": "${days}T verbleibend",
  "console.projects.statusToggle.markedToast": "Markiert als ${next}",
  "console.projects.statusToggle.updating": "Wird aktualisiert…",
  "console.projects.statusToggle.markAction": "Als ${next} markieren",
  "console.projects.advancing.transition.movedToast": "Verschoben nach ${toTitle(to)}",
  "console.projects.advancing.transition.failedToast": "Übergang fehlgeschlagen",
  "console.projects.advancing.assignments.new.title": "Neue Einzelzuweisung",
  "console.projects.advancing.assignments.new.submit": "Zuweisung erstellen",
  "console.projects.advancing.assignments.new.catalogItem": "Katalogposition",
  "console.projects.advancing.assignments.new.noCatalogSuffix": "zuerst.",
  "console.projects.advancing.assignments.new.titleLabel": "Titel",
  "console.projects.advancing.assignments.new.assignee": "Empfänger",
  "console.projects.advancing.assignments.new.deadline": "Deadline",
  "console.projects.advancing.assignments.new.notes": "Notizen (optional)",
  "console.projects.advancing.assignments.eyebrow": "Advancing",
  "console.projects.advancing.assignments.title": "Einzelzuweisungen",
  "console.projects.advancing.assignments.configureSupabase": "Supabase konfigurieren.",
  "console.projects.advancing.assignments.guest": "Gast",
  "console.projects.advancing.assignments.unknownUser": "Unbekannter Nutzer",
  "console.projects.advancing.assignments.unknownCrew": "Unbekannte Crew",
  "console.projects.advancing.assignments.unassigned": "Nicht zugewiesen",
  "console.projects.advancing.assignments.assignmentSingular": "Zuweisung",
  "console.projects.advancing.assignments.assignmentPlural": "Zuweisungen",
  "console.projects.advancing.assignments.subtitleKinds": "Tickets, Credentials, Catering, Funk, Werkzeug, Equipment, Uniformen, Travel, Lodging, Fahrzeuge",
  "console.projects.advancing.assignments.newAssignment": "+ Neue Zuweisung",
  "console.projects.advancing.assignments.emptyTitle": "Noch keine Zuweisungen",
  "console.projects.advancing.assignments.columns.title": "Titel",
  "console.projects.advancing.assignments.columns.party": "Beteiligte",
  "console.projects.advancing.assignments.columns.state": "Status",
  "console.projects.advancing.assignments.columns.due": "Fällig",
  "console.projects.advancing.assignments.columns.updated": "Aktualisiert",
  "console.projects.advancing.assignments.untitled": "Ohne Titel",
  "console.projects.advancing.eyebrowFallback": "Projekt",
  "console.projects.advancing.title": "Advancing",
  "console.projects.advancing.breadcrumbs.projects": "Projekte",
  "console.projects.advancing.breadcrumbs.advancing": "Advancing",
  "console.projects.advancing.openPortalView": "Portal-Ansicht öffnen →",
  "console.projects.advancing.empty.title": "Noch keine Deliverables",
  "console.projects.advancing.columns.title": "Titel",
  "console.projects.advancing.columns.type": "Typ",
  "console.projects.advancing.columns.status": "Status",
  "console.projects.advancing.columns.version": "v",
  "console.projects.advancing.columns.deadline": "Deadline",
  "console.projects.advancing.columns.updated": "Aktualisiert",
  "console.projects.advancing.columns.actions": "Aktionen",
  "console.projects.advancing.untitled": "Ohne Titel",
  "console.projects.advancing.fulfilled": "Erfüllt",
  "console.projects.advancing.commentsAria": "Kommentare",
  "console.projects.advancing.activity.latestDeliverable": "Neueste Deliverable-Aktivität",
  "console.projects.advancing.activity.project": "Projektaktivität",
  "console.projects.assignments.detail.unassigned": "Nicht zugewiesen",
  "console.projects.assignments.detail.unknownCrew": "Unbekannte Crew",
  "console.projects.assignments.detail.guest": "Gast",
  "console.projects.assignments.detail.untitled": "Ohne Titel",
  "console.projects.assignments.detail.notes": "Notizen",
  "console.projects.assignments.detail.ticket.title": "Ticket-Details",
  "console.projects.assignments.detail.ticket.tier": "Tier",
  "console.projects.assignments.detail.ticket.zones": "Zonen (Komma)",
  "console.projects.assignments.detail.ticket.gates": "Gates (Komma)",
  "console.projects.assignments.detail.ticket.validFrom": "Gültig ab",
  "console.projects.assignments.detail.ticket.validUntil": "Gültig bis",
  "console.projects.assignments.detail.ticket.section": "Sektion",
  "console.projects.assignments.detail.ticket.row": "Reihe",
  "console.projects.assignments.detail.ticket.seat": "Sitz",
  "console.projects.assignments.detail.ticket.save": "Ticket-Details speichern",
  "console.projects.assignments.detail.credential.title": "Credential-Details",
  "console.projects.assignments.detail.credential.accessLevel": "Zugriffsstufe",
  "console.projects.assignments.detail.credential.issuedOn": "Ausgestellt am",
  "console.projects.assignments.detail.credential.expiresOn": "Läuft ab am",
  "console.projects.assignments.detail.credential.mustReturn": "Rückgabepflichtig",
  "console.projects.assignments.detail.credential.save": "Credential-Details speichern",
  "console.projects.assignments.detail.lodging.title": "Lodging-Details",
  "console.projects.assignments.detail.lodging.property": "Objekt",
  "console.projects.assignments.detail.lodging.room": "Zimmer",
  "console.projects.assignments.detail.lodging.checkIn": "Check-in",
  "console.projects.assignments.detail.lodging.checkOut": "Check-out",
  "console.projects.assignments.detail.lodging.confirmation": "Bestätigung",
  "console.projects.assignments.detail.lodging.save": "Lodging-Details speichern",
  "console.projects.assignments.detail.travel.title": "Travel-Details",
  "console.projects.assignments.detail.travel.mode": "Modus",
  "console.projects.assignments.detail.travel.flight": "Flug",
  "console.projects.assignments.detail.travel.ground": "Boden",
  "console.projects.assignments.detail.travel.rail": "Bahn",
  "console.projects.assignments.detail.travel.sea": "See",
  "console.projects.assignments.detail.travel.carrier": "Carrier",
  "console.projects.assignments.detail.travel.confirmation": "Bestätigung",
  "console.projects.assignments.detail.travel.from": "Von",
  "console.projects.assignments.detail.travel.to": "Nach",
  "console.projects.assignments.detail.travel.depart": "Abfahrt",
  "console.projects.assignments.detail.travel.arrive": "Ankunft",
  "console.projects.assignments.detail.travel.seat": "Sitz",
  "console.projects.assignments.detail.travel.save": "Travel-Details speichern",
  "console.projects.assignments.detail.vehicle.title": "Fahrzeug-Details",
  "console.projects.assignments.detail.vehicle.label": "Bezeichnung",
  "console.projects.assignments.detail.vehicle.plate": "Kennzeichen",
  "console.projects.assignments.detail.vehicle.pickedUp": "Abgeholt",
  "console.projects.assignments.detail.vehicle.returned": "Zurückgegeben",
  "console.projects.assignments.detail.vehicle.mileageStart": "Kilometerstand Start",
  "console.projects.assignments.detail.vehicle.mileageEnd": "Kilometerstand Ende",
  "console.projects.assignments.detail.vehicle.save": "Fahrzeug-Details speichern",
  "console.projects.assignments.detail.advanceState.title": "Advance-Status",
  "console.projects.assignments.detail.reassign.title": "Neu zuweisen",
  "console.projects.assignments.detail.comments.title": "Kommentare",
  "console.projects.assignments.detail.comments.empty": "Keine Kommentare.",
  "console.projects.assignments.detail.comments.post": "Kommentar senden",
  "console.projects.assignments.detail.unknown": "Unbekannt",
  "console.projects.assignments.detail.activity.title": "Aktivität",
  "console.projects.assignments.detail.activity.empty": "Keine Aktivität erfasst.",
  "console.projects.assignments.detail.activity.by": "von ${actor}",
  "console.projects.assignments.detail.system": "System",
  "console.projects.branding.submit": "Branding speichern",
  "console.projects.branding.accentColor.label": "Akzentfarbe",
  "console.projects.branding.accentForeground.label": "Akzent-Vordergrund",
  "console.projects.branding.logoUrl.label": "Logo-URL",
  "console.projects.branding.faviconUrl.label": "Favicon-URL",
  "console.projects.branding.faviconUrl.hint": "HTTPS-URL zu einem quadratischen 512×512 PNG.",
  "console.projects.branding.heroImageUrl.label": "Hero-Bild-URL",
  "console.projects.branding.ogImageUrl.label": "OG-Bild-URL",
  "console.projects.branding.ogImageUrl.hint": "Open-Graph-Sharing-Bild (1200×630).",
  "console.projects.branding.livePreview": "Live-Vorschau",
  "console.projects.branding.preview.primaryAction": "Primäre Aktion",
  "console.projects.branding.preview.secondary": "Sekundär",
  "console.projects.branding.title": "Branding",
  "console.projects.budget.eyebrowFallback": "Projekt",
  "console.projects.budget.title": "Budget",
  "console.projects.budget.empty.title": "Noch keine Budgets",
  "console.projects.budget.empty.action": "Neues Budget →",
  "console.projects.breadcrumbs.projects": "Projekte",
  "console.projects.crew.eyebrowFallback": "Projekt",
  "console.projects.crew.title": "Crew",
  "console.projects.crew.subtitleOne": "${crew?.length ?? 0} Roster-Mitglied",
  "console.projects.crew.breadcrumbProjects": "Projekte",
  "console.projects.crew.emptyTitle": "Keine Crew im Roster",
  "console.projects.crew.columnName": "Name",
  "console.projects.crew.columnRole": "Rolle",
  "console.projects.crew.columnEmail": "E-Mail",
  "console.projects.crew.columnDayRate": "Tagessatz",
  "console.projects.edit.eyebrow": "Projekt",
  "console.projects.edit.title": "${row.name} bearbeiten",
  "console.projects.edit.submit": "Änderungen speichern",
  "console.projects.edit.fields.name": "Name",
  "console.projects.edit.fields.state": "Status",
  "console.projects.edit.fields.startDate": "Startdatum",
  "console.projects.edit.fields.endDate": "Enddatum",
  "console.projects.edit.fields.client": "Kunde",
  "console.projects.edit.fields.primaryVenue": "Primärer Veranstaltungsort",
  "console.projects.edit.fields.budget": "Budget",
  "console.projects.edit.fields.budgetHint": "Dollar. Als Integer-Cent gespeichert.",
  "console.projects.edit.fields.scope": "Scope",
  "console.projects.edit.fields.tourStructure": "Tour-Struktur",
  "console.projects.edit.fields.productionStyle": "Produktionsstil",
  "console.projects.edit.fields.description": "Beschreibung",
  "console.projects.edit.state.draft": "Entwurf",
  "console.projects.edit.state.active": "Aktiv",
  "console.projects.edit.state.paused": "Pausiert",
  "console.projects.edit.state.archived": "Archiviert",
  "console.projects.edit.state.complete": "Abgeschlossen",
  "console.projects.edit.none": "— Keine —",
  "console.projects.edit.scope.local": "Lokal",
  "console.projects.edit.scope.regional": "Regional",
  "console.projects.edit.scope.national": "National",
  "console.projects.edit.scope.international": "International",
  "console.projects.edit.tourStructure.singleStop": "Single Stop",
  "console.projects.edit.tourStructure.multiStopSequential": "Multi-Stop Sequenziell",
  "console.projects.edit.tourStructure.simultaneousMultiCity": "Simultan Multi-City",
  "console.projects.edit.productionStyle.editorial": "Editorial",
  "console.projects.edit.productionStyle.documentary": "Dokumentarisch",
  "console.projects.edit.productionStyle.narrative": "Narrativ",
  "console.projects.edit.productionStyle.spectacle": "Spektakel",
  "console.projects.edit.productionStyle.intimate": "Intim",
  "console.projects.edit.productionStyle.brutalist": "Brutalistisch",
  "console.projects.files.eyebrowFallback": "Projekt",
  "console.projects.files.title": "Dateien",
  "console.projects.files.breadcrumbProjects": "Projekte",
  "console.projects.files.breadcrumbFiles": "Dateien",
  "console.projects.files.emptyTitle": "Keine Dateien hochgeladen",
  "console.projects.files.untitled": "Ohne Titel",
  "console.projects.finance.title": "P&L",
  "console.projects.finance.configureSupabase": "Supabase konfigurieren.",
  "console.projects.finance.notFoundTitle": "Projekt nicht gefunden",
  "console.projects.finance.notFoundBody": "Projekt in diesem Workspace nicht gefunden.",
  "console.projects.finance.marginLabel": "Marge",
  "console.projects.finance.breadcrumbs.projects": "Projekte",
  "console.projects.finance.metrics.revenue": "Umsatz (bezahlt)",
  "console.projects.finance.metrics.spent": "Ausgegeben (committed)",
  "console.projects.finance.metrics.margin": "Marge",
  "console.projects.finance.metrics.outstanding": "Offene Rechnungen",
  "console.projects.finance.metrics.expensesCommitted": "Ausgaben committed",
  "console.projects.finance.metrics.posCommitted": "POs committed",
  "console.projects.finance.marginPctSentence": "Dieses Projekt liegt bei ${marginPct}% Marge gegenüber bezahltem Umsatz.",
  "console.projects.finance.budget.title": "Budget-Rahmen",
  "console.projects.finance.budget.open": "Budget öffnen →",
  "console.projects.finance.budget.overBudget": "über Budget",
  "console.projects.finance.invoices.title": "Rechnungen",
  "console.projects.finance.invoices.allLink": "Alle Rechnungen →",
  "console.projects.finance.invoices.emptyLabel": "Noch keine Rechnungen",
  "console.projects.finance.columns.number": "Nummer",
  "console.projects.finance.columns.title": "Titel",
  "console.projects.finance.columns.amount": "Betrag",
  "console.projects.finance.columns.status": "Status",
  "console.projects.finance.columns.due": "Fällig",
  "console.projects.finance.columns.description": "Beschreibung",
  "console.projects.finance.columns.category": "Kategorie",
  "console.projects.finance.columns.date": "Datum",
  "console.projects.finance.purchaseOrders.title": "Bestellungen",
  "console.projects.finance.purchaseOrders.allLink": "Alle POs →",
  "console.projects.finance.purchaseOrders.emptyLabel": "Keine Bestellungen",
  "console.projects.finance.expenses.title": "Ausgaben",
  "console.projects.finance.expenses.allLink": "Alle Ausgaben →",
  "console.projects.finance.expenses.emptyLabel": "Keine Ausgaben erfasst",
  "console.projects.guides.editor.savedToast": "Guide gespeichert",
  "console.projects.guides.editor.titleLabel": "Titel",
  "console.projects.guides.editor.subtitleLabel": "Untertitel",
  "console.projects.guides.editor.classificationLabel": "Klassifizierungs-Banner",
  "console.projects.guides.editor.publishedLabel": "Veröffentlicht (sichtbar im Portal + Mobile)",
  "console.projects.guides.editor.configLabel": "Konfiguration (JSON)",
  "console.projects.guides.editor.sectionsLabel": "Abschnitte:",
  "console.projects.guides.editor.saving": "Wird gespeichert…",
  "console.projects.guides.editor.saveButton": "Guide speichern",
  "console.projects.guides.access.issueTitle": "Neuen Code ausgeben",
  "console.projects.guides.access.labelField": "Bezeichnung",
  "console.projects.guides.access.expiresField": "Läuft ab in (Tage)",
  "console.projects.guides.access.expiresPlaceholder": "optional",
  "console.projects.guides.access.maxUsesField": "Maximale Nutzungen",
  "console.projects.guides.access.maxUsesPlaceholder": "unbegrenzt",
  "console.projects.guides.access.generating": "Wird generiert…",
  "console.projects.guides.access.generate": "Code generieren",
  "console.projects.guides.access.copyShareEyebrow": "Kopieren und teilen — wird nur einmal angezeigt",
  "console.projects.guides.access.copyCode": "Code kopieren",
  "console.projects.guides.access.activeCodes": "Aktive Codes",
  "console.projects.guides.access.noCodesIssued": "Keine Codes ausgegeben",
  "console.projects.guides.access.colPrefix": "Präfix",
  "console.projects.guides.access.colLabel": "Bezeichnung",
  "console.projects.guides.access.colCreated": "Erstellt",
  "console.projects.guides.access.colExpires": "Läuft ab",
  "console.projects.guides.access.colUses": "Nutzungen",
  "console.projects.guides.access.colActionsAria": "Aktionen",
  "console.projects.guides.access.never": "nie",
  "console.projects.guides.access.revoke": "Widerrufen",
  "console.projects.guides.access.colRevoked": "Widerrufen",
  "console.projects.guides.access.recentRedemptions": "Letzte Einlösungen",
  "console.projects.guides.access.noCodeUse": "Keine Code-Nutzung",
  "console.projects.guides.access.colWhen": "Wann",
  "console.projects.guides.access.colCode": "Code",
  "console.projects.guides.access.colIp": "IP",
  "console.projects.guides.access.colAgent": "Agent",
  "console.projects.guides.access.tipBadge": "Tipp",
  "console.projects.guides.access.publicBadge": "Öffentlich — kein Code erforderlich",
  "console.projects.guides.access.publicUrlLabel": "Öffentliche URL:",
  "console.projects.guides.access.editGuideContent": "Guide-Inhalt bearbeiten",
  "console.projects.guides.access.persona.staff": "Produktion",
  "console.projects.guides.access.persona.crew": "Operations",
  "console.projects.guides.access.persona.vendor": "Food & Beverage",
  "console.projects.guides.access.persona.brand_ambassador": "Brand Ambassador",
  "console.projects.guides.access.persona.sponsor": "Sponsoren",
  "console.projects.guides.access.persona.artist": "Talent",
  "console.projects.guides.access.persona.media_press": "Media & Press",
  "console.projects.guides.access.persona.client": "Kunde",
  "console.projects.guides.access.persona.guest": "Gäste",
  "console.projects.guides.access.persona.custom": "Temporärer Zugang",
  "console.projects.guides.persona.manageAccessCodes": "Zugangscodes verwalten",
  "console.projects.guides.title": "Event-Guides",
  "console.projects.guides.subtitle": "Know-before-you-go nach Rolle.",
  "console.projects.guides.statusLive": "Live",
  "console.projects.guides.statusDraft": "Entwurf",
  "console.projects.guides.statusNone": "Keine",
  "console.projects.guides.customHeading": "Custom Guide",
  "console.projects.guides.startCustom": "Custom Guide starten",
  "console.projects.tabs.overview": "Übersicht",
  "console.projects.tabs.tracker": "Tracker",
  "console.projects.tabs.tasks": "Aufgaben",
  "console.projects.tabs.schedule": "Zeitplan",
  "console.projects.tabs.files": "Dateien",
  "console.projects.tabs.photos": "Fotos",
  "console.projects.tabs.budget": "Budget",
  "console.projects.tabs.finance": "P&L",
  "console.projects.tabs.crew": "Crew",
  "console.projects.tabs.members": "Mitglieder",
  "console.projects.tabs.advancing": "Advancing",
  "console.projects.tabs.guides": "Guides",
  "console.projects.tabs.sustainability": "Nachhaltigkeit",
  "console.projects.members.addedToast": "Mitglied hinzugefügt",
  "console.projects.members.peopleInvitesLink": "People → Einladungen",
  "console.projects.members.noCandidatesSuffix": "zuerst.",
  "console.projects.members.orgMemberLabel": "Org-Mitglied",
  "console.projects.members.selectMemberPlaceholder": "Mitglied auswählen…",
  "console.projects.members.projectRoleLabel": "Projektrolle",
  "console.projects.members.addingButton": "Wird hinzugefügt",
  "console.projects.members.addButton": "Hinzufügen",
  "console.projects.members.removedToast": "Mitglied entfernt",
  "console.projects.members.roleForAria": "Rolle für ${member.email}",
  "console.projects.members.leaveButton": "Verlassen",
  "console.projects.members.removeButton": "Entfernen",
  "console.projects.members.title": "Mitglieder",
  "console.projects.members.subtitleOne": "${members.length} Projektmitglied",
  "console.projects.members.emptyTitle": "Keine Projektmitglieder",
  "console.projects.members.colMember": "Mitglied",
  "console.projects.members.colRole": "Rolle",
  "console.projects.breadcrumb": "Projekte",
  "console.projects.onboarding.eyebrow": "Onboarding",
  "console.projects.onboarding.col.recipient": "Empfänger",
  "console.projects.onboarding.col.progress": "Fortschritt",
  "console.projects.onboarding.col.criticalPathOpen": "Kritischer Pfad offen",
  "console.projects.onboarding.done": "Erledigt",
  "console.projects.overview.title": "Übersicht",
  "console.projects.overview.starts": "Beginn",
  "console.projects.overview.ends": "Ende",
  "console.projects.overview.tasks": "Aufgaben",
  "console.projects.overview.events": "Events",
  "console.projects.overview.budget": "Budget",
  "console.projects.overview.spent": "Ausgegeben",
  "console.projects.overview.deliverables": "Deliverables",
  "console.projects.detail.eyebrow": "Projekt",
  "console.projects.detail.noDescription": "Keine Beschreibung",
  "console.projects.detail.breadcrumbs.plan": "Plan",
  "console.projects.detail.breadcrumbs.projects": "Projekte",
  "console.projects.detail.archive": "Archivieren",
  "console.projects.detail.fields.state": "Status",
  "console.projects.detail.fields.slug": "Slug",
  "console.projects.detail.fields.start": "Beginn",
  "console.projects.detail.fields.end": "Ende",
  "console.projects.detail.fields.budget": "Budget",
  "console.projects.detail.fields.created": "Erstellt",
  "console.projects.detail.fields.updated": "Aktualisiert",
  "console.projects.detail.descriptionHeading": "Beschreibung",
  "console.projects.detail.noDescriptionYet": "Noch keine Beschreibung hinterlegt.",
  "console.projects.detail.externalPortal.heading": "Externes Portal",
  "console.projects.detail.commentsAria": "Kommentare",
  "console.projects.photos.eyebrow": "Projekt",
  "console.projects.photos.title": "Fotos",
  "console.projects.photos.subtitleEmpty": "Feld-Fotos, hochgeladen für dieses Projekt.",
  "console.projects.photos.emptyTitle": "Keine Fotos",
  "console.projects.photos.untitled": "Ohne Titel",
  "console.projects.portalPreview.projectFallback": "Projekt",
  "console.projects.portalPreview.title": "Portal-Vorschau",
  "console.projects.portalPreview.previewBadge": "Vorschau",
  "console.projects.roadmap.unscheduled": "Ungeplant",
  "console.projects.roadmap.eyebrowFallback": "Projekt",
  "console.projects.roadmap.title": "Roadmap",
  "console.projects.roadmap.subtitle": "Quartalsansicht von Aufgaben und Meilensteinen",
  "console.projects.roadmap.breadcrumbProjects": "Projekte",
  "console.projects.roadmap.emptyTitle": "Roadmap leer",
  "console.projects.roadmap.kindTask": "Aufgabe",
  "console.projects.roadmap.kindMilestone": "Meilenstein",
  "console.projects.schedule.board.empty": "Nichts zu boarden.",
  "console.projects.schedule.board.kindTask": "T",
  "console.projects.schedule.board.kindEvent": "E",
  "console.projects.schedule.calendar.previousMonth": "Vorheriger Monat",
  "console.projects.schedule.calendar.nextMonth": "Nächster Monat",
  "console.projects.schedule.calendar.weekday.sun": "So",
  "console.projects.schedule.calendar.weekday.mon": "Mo",
  "console.projects.schedule.calendar.weekday.tue": "Di",
  "console.projects.schedule.calendar.weekday.wed": "Mi",
  "console.projects.schedule.calendar.weekday.thu": "Do",
  "console.projects.schedule.calendar.weekday.fri": "Fr",
  "console.projects.schedule.calendar.weekday.sat": "Sa",
  "console.projects.schedule.calendar.eventStatusDraft": "Entwurf",
  "console.projects.schedule.calendar.taskStatusOpen": "offen",
  "console.projects.schedule.map.emptyPrefix": "Noch kein Event mit Standort. Setze ",
  "console.projects.schedule.map.emptySuffix": " an einem Event, um es zu mappen.",
  "console.projects.schedule.map.unassigned": "Nicht zugewiesen",
  "console.projects.schedule.table.empty": "Nichts anzuzeigen.",
  "console.projects.schedule.table.title": "Titel",
  "console.projects.schedule.table.kind": "Art",
  "console.projects.schedule.table.status": "Status",
  "console.projects.schedule.table.when": "Wann",
  "console.projects.schedule.table.end": "Ende",
  "console.projects.schedule.timeline.title": "Timeline",
  "console.projects.schedule.timeline.ariaLabel": "Projekt-Timeline",
  "console.projects.schedule.timeline.today": "Heute",
  "console.projects.schedule.timeline.lane.tasks": "Aufgaben",
  "console.projects.schedule.timeline.lane.events": "Events",
  "console.projects.schedule.taskSingular": "Aufgabe",
  "console.projects.schedule.taskPlural": "Aufgaben",
  "console.projects.schedule.eventSingular": "Event",
  "console.projects.schedule.eventPlural": "Events",
  "console.projects.schedule.nothingScheduled": "Nichts geplant",
  "console.projects.schedule.projectEyebrow": "Projekt",
  "console.projects.schedule.title": "Zeitplan",
  "console.projects.schedule.breadcrumbProjects": "Projekte",
  "console.projects.schedule.viewSwitcherAria": "Zeitplan-Ansicht",
  "console.projects.schedule.newEvent": "+ Neues Event",
  "console.projects.schedule.emptyTitle": "Noch nichts geplant",
  "console.projects.schedule.scheduleFirstEvent": "Erstes Event planen →",
  "console.projects.schedule.list.eventsHeading": "Events",
  "console.projects.schedule.list.tasksHeading": "Aufgaben",
  "console.projects.schedule.list.noDueDate": "Kein Fälligkeitsdatum",
  "console.projects.stagePlots.edit.eyebrow": "Stage Plot",
  "console.projects.stagePlots.edit.title": "${row.name} bearbeiten",
  "console.projects.stagePlots.edit.nameLabel": "Name",
  "console.projects.stagePlots.edit.widthLabel": "Breite (ft)",
  "console.projects.stagePlots.edit.depthLabel": "Tiefe (ft)",
  "console.projects.stagePlots.edit.notesLabel": "Notizen",
  "console.projects.stagePlots.detail.projectFallback": "Projekt",
  "console.projects.stagePlots.detail.subtitle": "Drag-and-Drop 2D-Stage-Layout-Editor",
  "console.projects.stagePlots.detail.breadcrumbs.projects": "Projekte",
  "console.projects.stagePlots.detail.breadcrumbs.stagePlots": "Stage Plots",
  "console.projects.stagePlots.detail.editMetadata": "Metadaten bearbeiten",
  "console.projects.stagePlots.eyebrowFallback": "Projekt",
  "console.projects.stagePlots.title": "Stage Plots",
  "console.projects.stagePlots.breadcrumbProjects": "Projekte",
  "console.projects.stagePlots.colName": "Name",
  "console.projects.stagePlots.colDimensions": "Maße",
  "console.projects.stagePlots.colLastUpdated": "Zuletzt aktualisiert",
  "console.projects.stagePlots.emptyPrefix": "Noch keine Stage Plots. Klicke",
  "console.projects.stagePlots.emptyAction": "Neuer Stage Plot",
  "console.projects.stagePlots.emptySuffix": "oben, um den Canvas-Editor zu öffnen.",
  "console.projects.sustainability.eyebrow": "Projekt",
  "console.projects.sustainability.title": "Nachhaltigkeit",
  "console.projects.sustainability.subtitle": "CO2-Emissionen auf Org-Ebene.",
  "console.projects.sustainability.empty.title": "Noch keine Metriken",
  "console.projects.sustainability.metrics.scope1": "Scope 1",
  "console.projects.sustainability.metrics.scope2": "Scope 2",
  "console.projects.sustainability.metrics.scope3": "Scope 3",
  "console.projects.sustainability.metrics.total": "Gesamt",
  "console.projects.tasks.eyebrowFallback": "Projekt",
  "console.projects.tasks.title": "Aufgaben",
  "console.projects.tasks.countNoun": "Aufgabe",
  "console.projects.tasks.breadcrumbProjects": "Projekte",
  "console.projects.tasks.emptyTitle": "Noch keine Aufgaben",
  "console.projects.tasks.newTaskCta": "Neue Aufgabe →",
  "console.projects.tasks.colTitle": "Titel",
  "console.projects.tasks.colStatus": "Status",
  "console.projects.tasks.colPriority": "Priorität",
  "console.projects.tasks.colDue": "Fällig",
  "console.projects.tracker.title": "Tracker",
  "console.projects.tracker.atomSingular": "Atom",
  "console.projects.tracker.atomPlural": "Atome",
  "console.projects.tracker.phase": "Phase",
  "console.projects.tracker.breadcrumb": "Tracker",
  "console.projects.tracker.openCatalog": "Katalog öffnen →",
  "console.projects.new.projectName": "Projektname",
  "console.projects.new.description": "Beschreibung",
  "console.projects.new.startDate": "Startdatum",
  "console.projects.new.endDate": "Enddatum",
  "console.projects.new.client": "Kunde",
  "console.projects.new.none": "— Keine —",
  "console.projects.new.primaryVenue": "Primärer Veranstaltungsort",
  "console.projects.new.budgetUsd": "Budget (USD)",
  "console.projects.new.budgetPlaceholder": "z. B. 1500000",
  "console.projects.new.geographicScope": "Geografischer Scope",
  "console.projects.new.scope.local": "Lokal",
  "console.projects.new.scope.regional": "Regional",
  "console.projects.new.scope.national": "National",
  "console.projects.new.scope.international": "International",
  "console.projects.new.tourStructure": "Tour-Struktur",
  "console.projects.new.tour.singleStop": "Single Stop",
  "console.projects.new.tour.multiStopSequential": "Multi-Stop Sequenziell",
  "console.projects.new.tour.simultaneousMultiCity": "Simultan Multi-City",
  "console.projects.new.productionStyle": "Produktionsstil",
  "console.projects.new.style.editorial": "Editorial",
  "console.projects.new.style.documentary": "Dokumentarisch",
  "console.projects.new.style.narrative": "Narrativ",
  "console.projects.new.style.spectacle": "Spektakel",
  "console.projects.new.style.intimate": "Intim",
  "console.projects.new.style.brutalist": "Brutalistisch",
  "console.projects.new.creating": "Wird erstellt…",
  "console.projects.new.createProject": "Projekt erstellen",
  "console.projects.new.title": "Neues Projekt",
  "console.projects.new.subtitle": "Erstelle ein Projekt für deine Organisation",
  "console.projects.title": "Projekte",
  "console.projects.configureSupabase": "Supabase konfigurieren, um Projekte zu laden.",
  "console.projects.totalCount": "${projects.length} Gesamt",
  "console.projects.newProject": "+ Neues Projekt",
  "console.projects.emptyTitle": "Noch keine Projekte",
  "console.projects.createFirst": "Erstelle dein erstes Projekt",
  "console.projects.emptyLabel": "Keine Projekte",
  "console.projects.columns.name": "Name",
  "console.projects.columns.slug": "Slug",
  "console.projects.columns.state": "Status",
  "console.projects.columns.start": "Beginn",
  "console.projects.columns.end": "Ende",
  "console.projects.columns.updated": "Aktualisiert"
}
