{
  "console.marketing.eyebrow": "Marketing",
  "console.marketing.calendar.title": "Kalender",
  "console.marketing.calendar.configureSupabase": "Supabase konfigurieren.",
  "console.marketing.calendar.empty": "Keine Meilensteine in den nächsten zwei Wochen.",
  "console.marketing.onsales.eyebrow": "Marketing",
  "console.marketing.onsales.title": "On-Sales",
  "console.marketing.onsales.configureSupabase": "Supabase konfigurieren.",
  "console.marketing.onsales.emptyLabel": "Keine bevorstehenden On-Sales",
  "console.marketing.onsales.col.kind": "Typ",
  "console.marketing.onsales.col.label": "Bezeichnung",
  "console.marketing.onsales.col.occurs": "Findet statt",
  "console.marketing.onsales.col.visibility": "Sichtbarkeit",
  "console.marketing.title": "Übersicht",
  "console.marketing.configureSupabase": "Supabase konfigurieren.",
  "console.marketing.subtitleOne": "${rows.length} Bevorstehender Meilenstein",
  "console.marketing.subtitleOther": "${rows.length} Bevorstehende Meilensteine",
  "console.marketing.metrics.onsales": "On-Sales",
  "console.marketing.metrics.presales": "Pre-Sales",
  "console.marketing.metrics.allMilestones": "Alle Meilensteine",
  "console.marketing.cards.onsales.title": "On-Sales",
  "console.marketing.cards.onsales.description": "Bevorstehende On-Sale-Termine über alle Shows.",
  "console.marketing.cards.calendar.title": "Kalender",
  "console.marketing.upcoming": "Bevorstehend",
  "console.marketing.viewCalendar": "Kalender ansehen"
}
