{
  "console.accreditation.categories.edit.categoryFallback": "Categoria",
  "console.accreditation.categories.edit.eyebrow": "Credenciamento · Categoria",
  "console.accreditation.categories.edit.codeLabel": "Código",
  "console.accreditation.categories.edit.nameLabel": "Nome",
  "console.accreditation.categories.edit.descriptionLabel": "Descrição",
  "console.accreditation.categories.edit.colorLabel": "Cor",
  "console.accreditation.categories.detail.title": "Categoria",
  "console.accreditation.categories.detail.configureSupabase": "Configure o Supabase.",
  "console.accreditation.categories.detail.eyebrow": "Credenciamento · Categoria",
  "console.accreditation.categories.new.eyebrow": "Credenciamento",
  "console.accreditation.categories.new.title": "Nova Categoria",
  "console.accreditation.categories.new.submit": "Adicionar Categoria",
  "console.accreditation.categories.new.codeLabel": "Código",
  "console.accreditation.categories.new.codePlaceholder": "ex.: ATL, OFF, MED",
  "console.accreditation.categories.new.nameLabel": "Nome",
  "console.accreditation.categories.new.namePlaceholder": "ex.: Atletas",
  "console.accreditation.categories.new.descriptionLabel": "Descrição",
  "console.accreditation.categories.new.colorLabel": "Cor (hex ou token)",
  "console.accreditation.categories.new.colorPlaceholder": "hex ou var(--token)",
  "console.accreditation.categories.eyebrowWorkspace": "Workspace",
  "console.accreditation.categories.title": "Categorias",
  "console.accreditation.categories.configureSupabase": "Configure o Supabase.",
  "console.accreditation.categories.eyebrow": "Credenciamento",
  "console.accreditation.categories.recordSingular": "Registro",
  "console.accreditation.categories.recordPlural": "Registros",
  "console.accreditation.categories.newCategory": "+ Nova Categoria",
  "console.accreditation.categories.emptyLabel": "Nenhuma categoria de credenciamento",
  "console.accreditation.categories.columns.code": "Código",
  "console.accreditation.categories.columns.name": "Nome",
  "console.accreditation.categories.columns.description": "Descrição",
  "console.accreditation.changes.edit.fallbackKind": "Alteração de credenciamento",
  "console.accreditation.changes.edit.eyebrow": "Alteração de Credenciamento",
  "console.accreditation.changes.edit.title": "Editar ${kindValue}",
  "console.accreditation.changes.edit.kindLabel": "Tipo",
  "console.accreditation.changes.edit.statusLabel": "Status",
  "console.accreditation.changes.edit.noteLabel": "Nota",
  "console.accreditation.changes.status.pending": "pendente",
  "console.accreditation.changes.status.approved": "aprovado",
  "console.accreditation.changes.status.rejected": "rejeitado",
  "console.accreditation.changes.status.applied": "aplicado",
  "console.accreditation.changes.detail.title": "Registro",
  "console.accreditation.changes.detail.configureSupabase": "Configure o Supabase.",
  "console.accreditation.changes.detail.eyebrow": "Registro",
  "console.accreditation.changes.eyebrow": "Credenciamento · Alterações",
  "console.accreditation.changes.new.title": "Nova Solicitação de Alteração",
  "console.accreditation.changes.new.goToAccreditation": "Ir para credenciamento",
  "console.accreditation.changes.new.submit": "Solicitar Alteração",
  "console.accreditation.changes.new.fields.accreditation": "Credenciamento",
  "console.accreditation.changes.new.fields.kind": "Tipo",
  "console.accreditation.changes.new.fields.note": "Nota",
  "console.accreditation.changes.new.fields.notePlaceholder": "Motivo / detalhe",
  "console.accreditation.changes.kinds.reissue": "Reemissão",
  "console.accreditation.changes.kinds.roleChange": "Mudança de função",
  "console.accreditation.changes.kinds.zoneChange": "Mudança de zona",
  "console.accreditation.changes.kinds.revocation": "Revogação",
  "console.accreditation.changes.kinds.lost": "Perdida / reposição",
  "console.accreditation.changes.kinds.other": "Outro",
  "console.accreditation.changes.eyebrowWorkspace": "Workspace",
  "console.accreditation.changes.titleFallback": "Alterações de Credenciamento",
  "console.accreditation.changes.configureSupabase": "Configure o Supabase.",
  "console.accreditation.changes.title": "Alterações",
  "console.accreditation.changes.recordSingular": "Registro",
  "console.accreditation.changes.recordPlural": "Registros",
  "console.accreditation.changes.requestChange": "+ Solicitar alteração",
  "console.accreditation.changes.emptyLabel": "Nenhuma alteração de credenciamento",
  "console.accreditation.changes.columnKind": "Tipo",
  "console.accreditation.changes.columnStatus": "Status",
  "console.accreditation.changes.columnRequested": "Solicitada",
  "console.accreditation.title": "Credenciamento",
  "console.accreditation.policy": "Política",
  "console.accreditation.zones": "Zonas",
  "console.accreditation.vetting": "Triagem",
  "console.accreditation.printQueue": "Fila de impressão",
  "console.accreditation.scans": "Leituras",
  "console.accreditation.print.eyebrowWorkspace": "Workspace",
  "console.accreditation.print.title": "Fila de Impressão",
  "console.accreditation.print.configureSupabase": "Configure o Supabase.",
  "console.accreditation.print.eyebrow": "Credenciamento",
  "console.accreditation.print.printSheet": "Folha de impressão",
  "console.accreditation.print.emptyLabel": "Nenhuma credencial na fila",
  "console.accreditation.print.columns.person": "Pessoa",
  "console.accreditation.print.columns.barcode": "Código de barras",
  "console.accreditation.print.columns.state": "Estado",
  "console.accreditation.print.sheet.title": "Folha de Impressão",
  "console.accreditation.print.sheet.configureSupabase": "Configure o Supabase.",
  "console.accreditation.print.sheet.eyebrow": "Credenciamento · Impressão",
  "console.accreditation.print.sheet.badgeSheetTitle": "Folha de Credenciais",
  "console.accreditation.print.sheet.empty": "Nenhuma credencial aprovada na fila.",
  "console.accreditation.print.sheet.orgFallback": "Org",
  "console.accreditation.print.sheet.validTo": "Válida até"
}
