{
  "console.transmittals.detail.eyebrow": "Transmittals",
  "console.transmittals.detail.projectFallback": "Projeto",
  "console.transmittals.detail.recipientSingular": "destinatário",
  "console.transmittals.detail.recipientPlural": "destinatários",
  "console.transmittals.detail.acknowledged": "confirmado",
  "console.transmittals.detail.itemSingular": "item",
  "console.transmittals.detail.itemPlural": "itens",
  "console.transmittals.detail.allTransmittals": "← Todos os Transmittals",
  "console.transmittals.detail.sent": "Enviado",
  "console.transmittals.detail.due": "Prazo",
  "console.transmittals.detail.send": "Enviar",
  "console.transmittals.detail.markClosed": "Marcar Como Encerrado",
  "console.transmittals.detail.body": "Corpo",
  "console.transmittals.detail.itemsHeading": "Itens",
  "console.transmittals.detail.itemType.sitePlan": "Planta do Local",
  "console.transmittals.detail.itemType.sheetSetVersion": "Versão do Conjunto de Pranchas",
  "console.transmittals.detail.itemType.specSection": "Seção de Especificação",
  "console.transmittals.detail.itemType.submittal": "Submittal",
  "console.transmittals.detail.itemType.rfi": "RFI",
  "console.transmittals.detail.itemType.deliverable": "Entregável",
  "console.transmittals.detail.itemType.file": "Arquivo",
  "console.transmittals.detail.uuidPlaceholder": "UUID",
  "console.transmittals.detail.addItem": "+ Adicionar Item",
  "console.transmittals.detail.recipientsHeading": "Destinatários",
  "console.transmittals.detail.cc": "CC",
  "console.transmittals.detail.acknowledgedBadge": "Confirmado",
  "console.transmittals.detail.delivered": "Entregue",
  "console.transmittals.detail.pending": "Pendente",
  "console.transmittals.detail.recipientKind.user": "Usuário da Org",
  "console.transmittals.detail.recipientKind.vendor": "Vendor",
  "console.transmittals.detail.recipientKind.externalEmail": "E-mail Externo",
  "console.transmittals.detail.userOption": "— usuário —",
  "console.transmittals.detail.vendorOption": "— vendor —",
  "console.transmittals.detail.emailPlaceholder": "email@…",
  "console.transmittals.detail.add": "+ Adicionar",
  "console.transmittals.new.eyebrow": "Operações",
  "console.transmittals.new.title": "Novo Transmittal",
  "console.transmittals.new.submit": "Criar Transmittal",
  "console.transmittals.new.subject": "Assunto",
  "console.transmittals.new.project": "Projeto",
  "console.transmittals.new.responseDue": "Prazo de resposta",
  "console.transmittals.new.bodyMarkdown": "Corpo (Markdown)",
  "console.transmittals.eyebrow": "Operações",
  "console.transmittals.title": "Transmittals",
  "console.transmittals.configureSupabase": "Configure o Supabase.",
  "console.transmittals.newTransmittal": "+ Novo Transmittal",
  "console.transmittals.metrics.total": "Total",
  "console.transmittals.metrics.sentOutstanding": "Enviados / Em Aberto",
  "console.transmittals.metrics.acknowledged": "Confirmados",
  "console.transmittals.metrics.draft": "Rascunho",
  "console.transmittals.empty.label": "Nenhum transmittal ainda",
  "console.transmittals.columns.code": "Código",
  "console.transmittals.columns.subject": "Assunto",
  "console.transmittals.columns.project": "Projeto",
  "console.transmittals.columns.sent": "Enviado",
  "console.transmittals.columns.due": "Prazo",
  "console.transmittals.columns.state": "Estado"
}
