{
  "console.agency.commissions.eyebrow": "エージェンシー",
  "console.agency.commissions.title": "コミッション",
  "console.agency.commissions.configureSupabase": "Supabase を設定してください。",
  "console.agency.commissions.totalBooked": "ブッキング総額",
  "console.agency.commissions.finalized": "確定済み",
  "console.agency.commissions.pending": "保留中",
  "console.agency.commissions.emptyLabel": "コミッションはまだ記録されていません",
  "console.agency.commissions.col.show": "公演",
  "console.agency.commissions.col.commission": "コミッション",
  "console.agency.commissions.col.artistPayout": "アーティスト支払",
  "console.agency.commissions.col.status": "ステータス",
  "console.agency.eyebrow": "エージェンシー",
  "console.agency.title": "概要",
  "console.agency.configureSupabase": "Supabase を設定してください。",
  "console.agency.subtitle": "ロスター、ツアー、コミッション管理。",
  "console.agency.metrics.agencies": "エージェンシー",
  "console.agency.metrics.activeRoster": "稼働中ロスター",
  "console.agency.metrics.activeTours": "稼働中ツアー",
  "console.agency.cards.roster.title": "ロスター",
  "console.agency.cards.tours.title": "ツアー",
  "console.agency.cards.tours.description": "連動するディール全体の複数日 P&L 集計。",
  "console.agency.cards.commissions.title": "コミッション",
  "console.agency.cards.commissions.description": "期間別コミッションレポート。",
  "console.agency.newTour": "+ 新規ツアー",
  "console.agency.roster.detail.eyebrow": "エージェンシー · ロスター",
  "console.agency.roster.detail.fallbackTitle": "ロスター項目",
  "console.agency.roster.detail.signedPrefix": "契約日",
  "console.agency.roster.detail.endedPrefix": "終了",
  "console.agency.roster.detail.exclusive": "専属",
  "console.agency.roster.detail.nonExclusive": "非専属",
  "console.agency.roster.detail.endedBadge": "終了",
  "console.agency.roster.detail.commissionLabel": "コミッション (bps; 1000 = 10%)",
  "console.agency.roster.detail.signedDateLabel": "契約日",
  "console.agency.roster.detail.exclusiveAgencyLabel": "専属エージェンシー",
  "console.agency.roster.detail.endRelationship": "契約終了",
  "console.agency.roster.eyebrow": "エージェンシー",
  "console.agency.roster.title": "ロスター",
  "console.agency.roster.configureSupabase": "Supabase を設定してください。",
  "console.agency.roster.subtitleOne": "稼働中アーティスト ${rows.length} 組",
  "console.agency.roster.subtitleOther": "稼働中アーティスト ${rows.length} 組",
  "console.agency.roster.emptyLabel": "ロスターはまだありません",
  "console.agency.roster.column.act": "アクト",
  "console.agency.roster.column.commission": "コミッション",
  "console.agency.roster.column.exclusive": "専属",
  "console.agency.roster.column.signed": "契約日",
  "console.agency.roster.commissionDefault": "既定値",
  "console.agency.tours.detail.eyebrow": "エージェンシー · ツアー",
  "console.agency.tours.detail.metrics.gbor": "GBOR",
  "console.agency.tours.detail.metrics.nbor": "NBOR",
  "console.agency.tours.detail.metrics.artistPayout": "アーティスト支払",
  "console.agency.tours.detail.metrics.ancillary": "付帯収益",
  "console.agency.tours.detail.legs.heading": "レッグ",
  "console.agency.tours.detail.legs.linkOffer": "オファーを紐付け →",
  "console.agency.tours.detail.legs.open": "開く →",
  "console.agency.tours.new.title": "新規ツアー",
  "console.agency.tours.new.subtitle": "複数日のルーティングコンテナ。",
  "console.agency.tours.new.submit": "ツアーを作成",
  "console.agency.tours.new.fields.name": "ツアー名",
  "console.agency.tours.new.fields.talent": "タレント",
  "console.agency.tours.new.fields.talentPlaceholder": "アクトを選択…",
  "console.agency.tours.new.fields.agencyOptional": "エージェンシー (任意)",
  "console.agency.tours.new.fields.starts": "開始",
  "console.agency.tours.new.fields.ends": "終了",
  "console.agency.tours.new.fields.description": "説明",
  "console.agency.tours.eyebrow": "エージェンシー",
  "console.agency.tours.title": "ツアー",
  "console.agency.tours.configureSupabase": "Supabase を設定してください。",
  "console.agency.tours.subtitleTourSingular": "ツアー",
  "console.agency.tours.subtitleTourPlural": "ツアー",
  "console.agency.tours.subtitleSuffix": "複数日 P&L 集計",
  "console.agency.tours.newTour": "+ 新規ツアー",
  "console.agency.tours.metric.totalGbor": "GBOR 合計",
  "console.agency.tours.metric.artistPayouts": "アーティスト支払",
  "console.agency.tours.metric.agentCommissions": "エージェントコミッション",
  "console.agency.tours.empty.label": "ツアーはまだありません",
  "console.agency.tours.col.tour": "ツアー",
  "console.agency.tours.col.status": "ステータス",
  "console.agency.tours.col.legs": "レッグ",
  "console.agency.tours.col.gbor": "GBOR",
  "console.agency.tours.col.nbor": "NBOR",
  "console.agency.tours.col.starts": "開始"
}
