{
  "console.pipeline.deal.eyebrow": "パイプライン",
  "console.pipeline.deal.breadcrumbs.sales": "セールス",
  "console.pipeline.deal.breadcrumbs.pipeline": "パイプライン",
  "console.pipeline.deal.metrics.value": "金額",
  "console.pipeline.deal.metrics.probability": "確度",
  "console.pipeline.deal.metrics.expectedClose": "クローズ予定日",
  "console.pipeline.deal.metrics.source": "ソース",
  "console.pipeline.deal.account.title": "アカウント",
  "console.pipeline.deal.account.notLinked": "アカウントに紐付けられていません。",
  "console.pipeline.deal.lifecycle.title": "ライフサイクル",
  "console.pipeline.deal.lifecycle.created": "作成日",
  "console.pipeline.deal.lifecycle.updated": "更新日",
  "console.pipeline.deal.lifecycle.closed": "クローズ日",
  "console.pipeline.deal.activity.title": "アクティビティ",
  "console.pipeline.eyebrow": "セールス",
  "console.pipeline.title": "パイプライン",
  "console.pipeline.configureSupabase": "Supabase を設定してください。",
  "console.pipeline.subtitleDefault": "ステージ別に整理された CRM ディールパイプライン",
  "console.pipeline.empty.title": "パイプラインがありません",
  "console.pipeline.metrics.openValue": "オープン金額",
  "console.pipeline.metrics.weighted": "加重金額",
  "console.pipeline.metrics.wonOpen": "受注(オープン)",
  "console.pipeline.noStages.title": "ステージがありません",
  "console.pipeline.lane.empty": "このステージにディールはありません。"
}
