{
  "console.finance.payApps.detail.set": "definir",
  "console.finance.payApps.new.eyebrow": "Finanzas",
  "console.finance.payApps.new.title": "Nueva Solicitud de Pago",
  "console.finance.payApps.new.submit": "Crear Borrador",
  "console.finance.payApps.new.purchaseOrder": "Orden de compra",
  "console.finance.payApps.new.periodStart": "Inicio del periodo",
  "console.finance.payApps.new.periodEnd": "Fin del periodo",
  "console.finance.payApps.new.retentionPct": "Retención %",
  "console.finance.payApps.new.notes": "Notas",
  "console.finance.payApps.eyebrow": "Finanzas",
  "console.finance.payApps.titleShort": "Pay Apps",
  "console.finance.payApps.configureSupabase": "Configura Supabase.",
  "console.finance.payApps.title": "Solicitudes de Pago",
  "console.finance.payApps.newCta": "+ Nueva Solicitud",
  "console.finance.payApps.metrics.pendingReview": "Pendiente de Revisión",
  "console.finance.payApps.metrics.netDue": "Neto a Pagar",
  "console.finance.payApps.metrics.completedYtd": "Completado YTD",
  "console.finance.payApps.emptyLabel": "Aún no hay solicitudes de pago",
  "console.finance.payApps.columns.application": "Solicitud",
  "console.finance.payApps.columns.po": "PO",
  "console.finance.payApps.columns.vendor": "Proveedor",
  "console.finance.payApps.columns.period": "Periodo",
  "console.finance.payApps.columns.completed": "Completado",
  "console.finance.payApps.columns.due": "A pagar",
  "console.finance.payApps.columns.status": "Estado",
  "console.finance.payouts.title": "Pagos",
  "console.finance.payouts.configureSupabase": "Configura Supabase.",
  "console.finance.payouts.eyebrow": "Finanzas",
  "console.finance.payouts.subtitle": "Estado de onboarding de Stripe Connect por proveedor",
  "console.finance.payouts.columns.vendor": "Proveedor",
  "console.finance.payouts.columns.connectAccount": "Cuenta Connect",
  "console.finance.payouts.columns.w9": "W-9",
  "console.finance.payouts.columns.coiExpires": "Vence COI",
  "console.finance.payouts.notOnboarded": "Sin Onboarding",
  "console.finance.payouts.onFile": "En Archivo",
  "console.finance.payouts.missing": "Falta",
  "console.finance.payroll.new.eyebrow": "Finanzas",
  "console.finance.payroll.new.title": "Nueva Corrida de Nómina",
  "console.finance.payroll.new.submit": "Crear Corrida",
  "console.finance.payroll.new.project": "Proyecto",
  "console.finance.payroll.new.selectPlaceholder": "Selecciona…",
  "console.finance.payroll.new.weekEnding": "Semana que termina",
  "console.finance.payroll.new.periodStart": "Inicio del periodo",
  "console.finance.payroll.new.periodEnd": "Fin del periodo",
  "console.finance.payroll.new.stateCode": "Código de estado",
  "console.finance.payroll.new.stateCodePlaceholder": "CA, NV, TX…",
  "console.finance.payroll.new.agencyReport": "Reporte de agencia",
  "console.finance.payroll.new.agency.none": "Ninguno",
  "console.finance.payroll.new.agency.wh347": "WH-347 (Federal Davis-Bacon)",
  "console.finance.payroll.new.agency.caDir": "CA DIR",
  "console.finance.payroll.new.agency.nyPwa": "NY PWA",
  "console.finance.payroll.new.agency.waLni": "WA L&I",
  "console.finance.payroll.new.agency.stateOther": "Otro estado",
  "console.finance.payroll.new.notes": "Notas",
  "console.finance.payroll.eyebrow": "Finanzas",
  "console.finance.payroll.title": "Nómina Certificada",
  "console.finance.payroll.configureSupabase": "Configura Supabase.",
  "console.finance.payroll.runSingular": "corrida",
  "console.finance.payroll.runPlural": "corridas",
  "console.finance.payroll.newRun": "+ Nueva Corrida de Nómina",
  "console.finance.payroll.metrics.outstanding": "Pendiente",
  "console.finance.payroll.metrics.submitted": "Enviado",
  "console.finance.payroll.metrics.grossYTD": "Bruto YTD",
  "console.finance.payroll.emptyLabel": "Aún no hay corridas de nómina",
  "console.finance.payroll.columns.weekEnding": "Semana que Termina",
  "console.finance.payroll.columns.project": "Proyecto",
  "console.finance.payroll.columns.agency": "Agencia",
  "console.finance.payroll.columns.state": "Estado",
  "console.finance.payroll.columns.hours": "Horas",
  "console.finance.payroll.columns.gross": "Bruto",
  "console.finance.payroll.columns.runState": "Estado",
  "console.finance.periods.controls.terminal": "Estado terminal — no hay más transiciones.",
  "console.finance.periods.controls.from": "Desde",
  "console.finance.periods.detail.eyebrow": "Periodo Contable",
  "console.finance.periods.detail.stateHeading": "Estado",
  "console.finance.periods.detail.frozenLabel": "Periodo congelado.",
  "console.finance.periods.detail.fullLogLink": "Registro completo →",
  "console.finance.periods.detail.noTransitions": "Aún no se han registrado transiciones.",
  "console.finance.periods.detail.initialState": "(inicial)",
  "console.finance.periods.transitions.title": "Transiciones de Estado",
  "console.finance.periods.transitions.col.when": "Cuándo",
  "console.finance.periods.transitions.col.from": "Desde",
  "console.finance.periods.transitions.col.to": "Hasta",
  "console.finance.periods.transitions.col.reason": "Motivo",
  "console.finance.periods.transitions.col.by": "Por",
  "console.finance.periods.transitions.initial": "(inicial)",
  "console.finance.periods.transitions.empty": "Aún no hay transiciones",
  "console.finance.periods.new.eyebrow": "Finanzas",
  "console.finance.periods.new.title": "Nuevo Periodo Contable",
  "console.finance.periods.new.subtitle": "Abre un mes, trimestre o periodo fiscal.",
  "console.finance.periods.new.labelLabel": "Etiqueta",
  "console.finance.periods.new.startsOn": "Inicia el",
  "console.finance.periods.new.endsOn": "Termina el",
  "console.finance.periods.new.openPeriod": "Abrir Periodo",
  "console.finance.periods.title": "Periodos Contables",
  "console.finance.periods.configureSupabase": "Configura Supabase.",
  "console.finance.periods.newCta": "+ Nuevo Periodo",
  "console.finance.periods.cols.label": "Etiqueta",
  "console.finance.periods.cols.range": "Rango",
  "console.finance.periods.cols.state": "Estado",
  "console.finance.periods.cols.closed": "Cerrado",
  "console.finance.periods.empty.label": "Aún no hay periodos contables",
  "console.finance.reports.charts.cumulativeRevenue.title": "Ingresos Acumulados",
  "console.finance.reports.charts.cumulativeRevenue.description": "Últimos 12 meses",
  "console.finance.reports.charts.cumulativeRevenue.seriesLabel": "Acumulado",
  "console.finance.reports.charts.revenueExpensesMargin.title": "Ingresos, gastos, margen",
  "console.finance.reports.charts.revenueExpensesMargin.description": "Últimos 12 meses",
  "console.finance.reports.charts.revenueExpensesMargin.revenue": "Ingresos",
  "console.finance.reports.charts.revenueExpensesMargin.expenses": "Gastos",
  "console.finance.reports.charts.revenueExpensesMargin.margin": "Margen",
  "console.finance.reports.charts.arAging.title": "Antigüedad de AR",
  "console.finance.reports.charts.arAging.outstanding": "Pendiente",
  "console.finance.reports.charts.topExpenseCategories.title": "Principales Categorías de Gasto",
  "console.finance.reports.title": "Reportes",
  "console.finance.reports.configureSupabase": "Configura Supabase.",
  "console.finance.reports.eyebrow": "Finanzas",
  "console.finance.reports.subtitle": "P&L en vivo desde los libros actuales",
  "console.finance.reports.metrics.revenuePaid": "Ingresos (pagados)",
  "console.finance.reports.metrics.expenses": "Gastos",
  "console.finance.reports.metrics.grossMargin": "Margen Bruto",
  "console.finance.reports.arAging.title": "Antigüedad de AR",
  "console.finance.reports.arAging.subtitle": "Facturas pendientes por días vencidos",
  "console.finance.reports.arAging.col.bucket": "Tramo",
  "console.finance.reports.arAging.col.invoices": "Facturas",
  "console.finance.reports.arAging.col.total": "Total",
  "console.finance.time.edit.fallbackDescription": "registro de tiempo",
  "console.finance.time.edit.eyebrow": "Registro de Tiempo",
  "console.finance.time.edit.fields.description": "Descripción",
  "console.finance.time.edit.fields.startedAt": "Inicio",
  "console.finance.time.edit.fields.endedAt": "Fin",
  "console.finance.time.edit.fields.durationMinutes": "Duración (minutos)",
  "console.finance.time.edit.fields.billable": "Facturable",
  "console.finance.time.entry.eyebrow": "Finanzas",
  "console.finance.time.entry.fallbackTitle": "Registro de tiempo",
  "console.finance.time.entry.breadcrumbs.finance": "Finanzas",
  "console.finance.time.entry.breadcrumbs.time": "Tiempo",
  "console.finance.time.entry.breadcrumbs.entry": "Registro",
  "console.finance.time.entry.fields.started": "Inicio",
  "console.finance.time.entry.fields.ended": "Fin",
  "console.finance.time.entry.fields.duration": "Duración",
  "console.finance.time.entry.fields.billable": "Facturable",
  "console.finance.time.entry.fields.description": "Descripción",
  "console.finance.time.new.submitLabel": "Registrar Tiempo",
  "console.finance.time.new.startedLabel": "Inicio",
  "console.finance.time.new.endedLabel": "Fin",
  "console.finance.time.new.descriptionLabel": "Descripción",
  "console.finance.time.new.billableLabel": "Facturable",
  "console.finance.time.new.eyebrow": "Finanzas",
  "console.finance.time.new.title": "Registrar Tiempo",
  "console.finance.time.title": "Control de Tiempo",
  "console.finance.time.configureSupabase": "Configura Supabase.",
  "console.finance.time.eyebrow": "Finanzas",
  "console.finance.time.newEntry": "+ Nuevo Registro",
  "console.finance.time.emptyLabel": "Sin registros de tiempo",
  "console.finance.time.columns.description": "Descripción",
  "console.finance.time.columns.duration": "Duración",
  "console.finance.time.columns.billable": "Facturable",
  "console.finance.time.columns.started": "Inicio",
  "console.finance.treasury.title": "Tesorería",
  "console.finance.treasury.configureSupabase": "Configura Supabase.",
  "console.finance.treasury.tiles.invoices.label": "Facturas",
  "console.finance.treasury.tiles.expenses.label": "Gastos",
  "console.finance.treasury.tiles.budgets.label": "Presupuestos",
  "console.finance.treasury.tiles.budgets.description": "Envolventes de P&L por proyecto",
  "console.finance.treasury.tiles.payouts.label": "Pagos",
  "console.finance.treasury.subtitle": "Posición de caja, cuentas por cobrar, cuentas por pagar.",
  "console.finance.treasury.metrics.outstandingReceivables": "Cuentas por Cobrar Pendientes",
  "console.finance.treasury.metrics.pendingPayables": "Cuentas por Pagar Pendientes",
  "console.finance.treasury.metrics.stripeEvents30d": "Eventos Stripe · 30d",
  "console.finance.treasury.byCurrency": "Por Moneda",
  "console.finance.treasury.noInvoices": "Aún no se han emitido facturas.",
  "console.finance.treasury.columns.currency": "Moneda",
  "console.finance.treasury.columns.paid": "Pagado",
  "console.finance.treasury.columns.outstanding": "Pendiente",
  "console.finance.treasury.columns.pendingPayables": "Cuentas por pagar pendientes",
  "console.finance.treasury.dueLabel": "vence {date}",
  "console.finance.treasury.drillIn": "Profundizar",
  "console.finance.wip.eyebrow": "Finanzas",
  "console.finance.wip.title": "WIP",
  "console.finance.wip.configureSupabase": "Configura Supabase.",
  "console.finance.wip.generateSnapshots": "Generar snapshots",
  "console.finance.wip.downloadLatestPdf": "Descargar Último PDF de WIP",
  "console.finance.wip.metric.aggregateContract": "Contrato Agregado",
  "console.finance.wip.metric.overBilledLatest": "Sobrefacturado (último)",
  "console.finance.wip.metric.underBilledLatest": "Subfacturado (último)",
  "console.finance.wip.emptyLabel": "Aún no hay snapshots de WIP",
  "console.finance.wip.addSnapshot": "+ Snapshot",
  "console.finance.wip.col.project": "Proyecto",
  "console.finance.wip.col.snapshot": "Snapshot",
  "console.finance.wip.col.contract": "Contrato (incl. CO)",
  "console.finance.wip.col.pctComp": "% Comp",
  "console.finance.wip.col.earned": "Devengado",
  "console.finance.wip.col.billed": "Facturado",
  "console.finance.wip.col.overUnder": "Sobre / Bajo",
  "console.finance.wip.overPrefix": "Sobre ",
  "console.finance.wip.underPrefix": "Bajo "
}
